gopython/__init__.py
gopython/const.py
gopython/dataclasses.py
gopython/hello.py
gopython/utils.py
gopython/wrapper.py
gopython/api/__init__.py
gopython/api/auth.py
gopython/api/permission.py
gopython/api/role.py
gopython/api/user.py
gopython-0.0.13.dist-info/METADATA
gopython-0.0.13.dist-info/WHEEL
gopython-0.0.13.dist-info/top_level.txt
gopython-0.0.13.dist-info/RECORD
